{
  "meta": {
    "href": "http://test.operon.systems/rest/v1/query/?aql=select%20a%20as%20data%20from%20EHR%20e%5Behr_id/value%3D'dabcbf61-94bb-45df-a472-9c7a489a200d'%5D%20contains%20COMPOSITION%20a%5BopenEHR-EHR-COMPOSITION.health_summary.v1%5D%20where%20a/name/value%3D'Relevant%20Contacts%20List'"
  },
  "aql": "select a as data from EHR e[ehr_id/value='dabcbf61-94bb-45df-a472-9c7a489a200d'] contains COMPOSITION a[openEHR-EHR-COMPOSITION.health_summary.v1] where a/name/value='Relevant Contacts List'",
  "executedAql": "select a as data from EHR e[ehr_id/value='dabcbf61-94bb-45df-a472-9c7a489a200d'] contains COMPOSITION a[openEHR-EHR-COMPOSITION.health_summary.v1] where a/name/value='Relevant Contacts List'",
  "resultSet": [
    {
      "data": {
        "@class": "COMPOSITION",
        "name": {
          "@class": "DV_TEXT",
          "value": "Relevant Contacts List"
        },
        "uid": {
          "@class": "OBJECT_VERSION_ID",
          "value": "96e5537f-600e-4334-aaad-629ecfaeadf8::hcbox.oprn.ehrscape.com::1"
        },
        "archetype_details": {
          "@class": "ARCHETYPED",
          "archetype_id": {
            "@class": "ARCHETYPE_ID",
            "value": "openEHR-EHR-COMPOSITION.health_summary.v1"
          },
          "template_id": {
            "@class": "TEMPLATE_ID",
            "value": "IDCR - Relevant contacts.v0"
          },
          "rm_version": "1.0.1"
        },
        "archetype_node_id": "openEHR-EHR-COMPOSITION.health_summary.v1",
        "language": {
          "@class": "CODE_PHRASE",
          "terminology_id": {
            "@class": "TERMINOLOGY_ID",
            "value": "ISO_639-1"
          },
          "code_string": "en"
        },
        "territory": {
          "@class": "CODE_PHRASE",
          "terminology_id": {
            "@class": "TERMINOLOGY_ID",
            "value": "ISO_3166-1"
          },
          "code_string": "GB"
        },
        "category": {
          "@class": "DV_CODED_TEXT",
          "value": "event",
          "defining_code": {
            "@class": "CODE_PHRASE",
            "terminology_id": {
              "@class": "TERMINOLOGY_ID",
              "value": "openehr"
            },
            "code_string": "433"
          }
        },
        "composer": {
          "@class": "PARTY_IDENTIFIED",
          "name": "Dr Tony Shannon"
        },
        "context": {
          "@class": "EVENT_CONTEXT",
          "start_time": {
            "@class": "DV_DATE_TIME",
            "value": "2017-06-11T00:11:02.518+02:00"
          },
          "setting": {
            "@class": "DV_CODED_TEXT",
            "value": "other care",
            "defining_code": {
              "@class": "CODE_PHRASE",
              "terminology_id": {
                "@class": "TERMINOLOGY_ID",
                "value": "openehr"
              },
              "code_string": "238"
            }
          },
          "health_care_facility": {
            "@class": "PARTY_IDENTIFIED",
            "external_ref": {
              "@class": "PARTY_REF",
              "id": {
                "@class": "GENERIC_ID",
                "value": "999999-345",
                "scheme": "2.16.840.1.113883.2.1.4.3"
              },
              "namespace": "NHS-UK",
              "type": "PARTY"
            },
            "name": "Home"
          }
        },
        "content": [
          {
            "@class": "SECTION",
            "name": {
              "@class": "DV_TEXT",
              "value": "Relevant contacts"
            },
            "archetype_details": {
              "@class": "ARCHETYPED",
              "archetype_id": {
                "@class": "ARCHETYPE_ID",
                "value": "openEHR-EHR-SECTION.relevant_contacts_rcp.v1"
              },
              "rm_version": "1.0.1"
            },
            "archetype_node_id": "openEHR-EHR-SECTION.relevant_contacts_rcp.v1",
            "items": [
              {
                "@class": "ADMIN_ENTRY",
                "name": {
                  "@class": "DV_TEXT",
                  "value": "Relevant contact"
                },
                "archetype_details": {
                  "@class": "ARCHETYPED",
                  "archetype_id": {
                    "@class": "ARCHETYPE_ID",
                    "value": "openEHR-EHR-ADMIN_ENTRY.relevant_contact_rcp.v1"
                  },
                  "rm_version": "1.0.1"
                },
                "archetype_node_id": "openEHR-EHR-ADMIN_ENTRY.relevant_contact_rcp.v1",
                "language": {
                  "@class": "CODE_PHRASE",
                  "terminology_id": {
                    "@class": "TERMINOLOGY_ID",
                    "value": "ISO_639-1"
                  },
                  "code_string": "en"
                },
                "encoding": {
                  "@class": "CODE_PHRASE",
                  "terminology_id": {
                    "@class": "TERMINOLOGY_ID",
                    "value": "IANA_character-sets"
                  },
                  "code_string": "UTF-8"
                },
                "subject": {
                  "@class": "PARTY_SELF"
                },
                "data": {
                  "@class": "ITEM_TREE",
                  "name": {
                    "@class": "DV_TEXT",
                    "value": "Tree"
                  },
                  "archetype_node_id": "at0001",
                  "items": [
                    {
                      "@class": "CLUSTER",
                      "name": {
                        "@class": "DV_TEXT",
                        "value": "Individual person"
                      },
                      "archetype_details": {
                        "@class": "ARCHETYPED",
                        "archetype_id": {
                          "@class": "ARCHETYPE_ID",
                          "value": "openEHR-EHR-CLUSTER.individual_person_uk.v1"
                        },
                        "rm_version": "1.0.1"
                      },
                      "archetype_node_id": "openEHR-EHR-CLUSTER.individual_person_uk.v1",
                      "items": [
                        {
                          "@class": "CLUSTER",
                          "name": {
                            "@class": "DV_TEXT",
                            "value": "Person name"
                          },
                          "archetype_details": {
                            "@class": "ARCHETYPED",
                            "archetype_id": {
                              "@class": "ARCHETYPE_ID",
                              "value": "openEHR-EHR-CLUSTER.person_name.v1"
                            },
                            "rm_version": "1.0.1"
                          },
                          "archetype_node_id": "openEHR-EHR-CLUSTER.person_name.v1",
                          "items": [
                            {
                              "@class": "ELEMENT",
                              "name": {
                                "@class": "DV_TEXT",
                                "value": "Unstructured name"
                              },
                              "archetype_node_id": "at0001",
                              "value": {
                                "@class": "DV_TEXT",
                                "value": "Andrew Finch"
                              }
                            }
                          ]
                        },
                        {
                          "@class": "CLUSTER",
                          "name": {
                            "@class": "DV_TEXT",
                            "value": "Address"
                          },
                          "archetype_details": {
                            "@class": "ARCHETYPED",
                            "archetype_id": {
                              "@class": "ARCHETYPE_ID",
                              "value": "openEHR-EHR-CLUSTER.address_uk.v0"
                            },
                            "rm_version": "1.0.1"
                          },
                          "archetype_node_id": "openEHR-EHR-CLUSTER.address_uk.v0",
                          "items": [
                            {
                              "@class": "ELEMENT",
                              "name": {
                                "@class": "DV_TEXT",
                                "value": "Address description"
                              },
                              "archetype_node_id": "at0002",
                              "value": {
                                "@class": "DV_TEXT",
                                "value": "The old Vicarage, Long Lane, Leeds"
                              }
                            }
                          ]
                        },
                        {
                          "@class": "CLUSTER",
                          "name": {
                            "@class": "DV_TEXT",
                            "value": "Contact details"
                          },
                          "archetype_details": {
                            "@class": "ARCHETYPED",
                            "archetype_id": {
                              "@class": "ARCHETYPE_ID",
                              "value": "openEHR-EHR-CLUSTER.telecom_uk.v1"
                            },
                            "rm_version": "1.0.1"
                          },
                          "archetype_node_id": "openEHR-EHR-CLUSTER.telecom_uk.v1",
                          "items": [
                            {
                              "@class": "ELEMENT",
                              "name": {
                                "@class": "DV_TEXT",
                                "value": "Comms description"
                              },
                              "archetype_node_id": "at0002",
                              "value": {
                                "@class": "DV_TEXT",
                                "value": "Mobile: 09876 413201"
                              }
                            }
                          ]
                        }
                      ]
                    },
                    {
                      "@class": "ELEMENT",
                      "name": {
                        "@class": "DV_TEXT",
                        "value": "Relationship category"
                      },
                      "archetype_node_id": "at0035",
                      "value": {
                        "@class": "DV_CODED_TEXT",
                        "value": "Informal carer",
                        "defining_code": {
                          "@class": "CODE_PHRASE",
                          "terminology_id": {
                            "@class": "TERMINOLOGY_ID",
                            "value": "local"
                          },
                          "code_string": "at0036"
                        }
                      }
                    },
                    {
                      "@class": "ELEMENT",
                      "name": {
                        "@class": "DV_TEXT",
                        "value": "Relationship/ role"
                      },
                      "archetype_node_id": "at0030",
                      "value": {
                        "@class": "DV_TEXT",
                        "value": "Son"
                      }
                    },
                    {
                      "@class": "ELEMENT",
                      "name": {
                        "@class": "DV_TEXT",
                        "value": "Is next of kin?"
                      },
                      "archetype_node_id": "at0025",
                      "value": {
                        "@class": "DV_BOOLEAN",
                        "value": true
                      }
                    },
                    {
                      "@class": "ELEMENT",
                      "name": {
                        "@class": "DV_TEXT",
                        "value": "Note"
                      },
                      "archetype_node_id": "at0017",
                      "value": {
                        "@class": "DV_TEXT",
                        "value": "Wife can assist if required."
                      }
                    }
                  ]
                }
              }
            ]
          }
        ]
      }
    },
    {
      "data": {
        "@class": "COMPOSITION",
        "name": {
          "@class": "DV_TEXT",
          "value": "Relevant Contacts List"
        },
        "uid": {
          "@class": "OBJECT_VERSION_ID",
          "value": "ce93e70c-3d21-4145-b92f-e39442dfedc5::hcbox.oprn.ehrscape.com::1"
        },
        "archetype_details": {
          "@class": "ARCHETYPED",
          "archetype_id": {
            "@class": "ARCHETYPE_ID",
            "value": "openEHR-EHR-COMPOSITION.health_summary.v1"
          },
          "template_id": {
            "@class": "TEMPLATE_ID",
            "value": "IDCR - Relevant contacts.v0"
          },
          "rm_version": "1.0.1"
        },
        "archetype_node_id": "openEHR-EHR-COMPOSITION.health_summary.v1",
        "language": {
          "@class": "CODE_PHRASE",
          "terminology_id": {
            "@class": "TERMINOLOGY_ID",
            "value": "ISO_639-1"
          },
          "code_string": "en"
        },
        "territory": {
          "@class": "CODE_PHRASE",
          "terminology_id": {
            "@class": "TERMINOLOGY_ID",
            "value": "ISO_3166-1"
          },
          "code_string": "GB"
        },
        "category": {
          "@class": "DV_CODED_TEXT",
          "value": "event",
          "defining_code": {
            "@class": "CODE_PHRASE",
            "terminology_id": {
              "@class": "TERMINOLOGY_ID",
              "value": "openehr"
            },
            "code_string": "433"
          }
        },
        "composer": {
          "@class": "PARTY_IDENTIFIED",
          "name": "Dr Tony Shannon"
        },
        "context": {
          "@class": "EVENT_CONTEXT",
          "start_time": {
            "@class": "DV_DATE_TIME",
            "value": "2016-02-24T00:11:02.518+02:00"
          },
          "setting": {
            "@class": "DV_CODED_TEXT",
            "value": "other care",
            "defining_code": {
              "@class": "CODE_PHRASE",
              "terminology_id": {
                "@class": "TERMINOLOGY_ID",
                "value": "openehr"
              },
              "code_string": "238"
            }
          },
          "health_care_facility": {
            "@class": "PARTY_IDENTIFIED",
            "external_ref": {
              "@class": "PARTY_REF",
              "id": {
                "@class": "GENERIC_ID",
                "value": "999999-345",
                "scheme": "2.16.840.1.113883.2.1.4.3"
              },
              "namespace": "NHS-UK",
              "type": "PARTY"
            },
            "name": "Home"
          }
        },
        "content": [
          {
            "@class": "SECTION",
            "name": {
              "@class": "DV_TEXT",
              "value": "Relevant contacts"
            },
            "archetype_details": {
              "@class": "ARCHETYPED",
              "archetype_id": {
                "@class": "ARCHETYPE_ID",
                "value": "openEHR-EHR-SECTION.relevant_contacts_rcp.v1"
              },
              "rm_version": "1.0.1"
            },
            "archetype_node_id": "openEHR-EHR-SECTION.relevant_contacts_rcp.v1",
            "items": [
              {
                "@class": "ADMIN_ENTRY",
                "name": {
                  "@class": "DV_TEXT",
                  "value": "Relevant contact"
                },
                "archetype_details": {
                  "@class": "ARCHETYPED",
                  "archetype_id": {
                    "@class": "ARCHETYPE_ID",
                    "value": "openEHR-EHR-ADMIN_ENTRY.relevant_contact_rcp.v1"
                  },
                  "rm_version": "1.0.1"
                },
                "archetype_node_id": "openEHR-EHR-ADMIN_ENTRY.relevant_contact_rcp.v1",
                "language": {
                  "@class": "CODE_PHRASE",
                  "terminology_id": {
                    "@class": "TERMINOLOGY_ID",
                    "value": "ISO_639-1"
                  },
                  "code_string": "en"
                },
                "encoding": {
                  "@class": "CODE_PHRASE",
                  "terminology_id": {
                    "@class": "TERMINOLOGY_ID",
                    "value": "IANA_character-sets"
                  },
                  "code_string": "UTF-8"
                },
                "subject": {
                  "@class": "PARTY_SELF"
                },
                "data": {
                  "@class": "ITEM_TREE",
                  "name": {
                    "@class": "DV_TEXT",
                    "value": "Tree"
                  },
                  "archetype_node_id": "at0001",
                  "items": [
                    {
                      "@class": "CLUSTER",
                      "name": {
                        "@class": "DV_TEXT",
                        "value": "Individual person"
                      },
                      "archetype_details": {
                        "@class": "ARCHETYPED",
                        "archetype_id": {
                          "@class": "ARCHETYPE_ID",
                          "value": "openEHR-EHR-CLUSTER.individual_person_uk.v1"
                        },
                        "rm_version": "1.0.1"
                      },
                      "archetype_node_id": "openEHR-EHR-CLUSTER.individual_person_uk.v1",
                      "items": [
                        {
                          "@class": "CLUSTER",
                          "name": {
                            "@class": "DV_TEXT",
                            "value": "Person name"
                          },
                          "archetype_details": {
                            "@class": "ARCHETYPED",
                            "archetype_id": {
                              "@class": "ARCHETYPE_ID",
                              "value": "openEHR-EHR-CLUSTER.person_name.v1"
                            },
                            "rm_version": "1.0.1"
                          },
                          "archetype_node_id": "openEHR-EHR-CLUSTER.person_name.v1",
                          "items": [
                            {
                              "@class": "ELEMENT",
                              "name": {
                                "@class": "DV_TEXT",
                                "value": "Unstructured name"
                              },
                              "archetype_node_id": "at0001",
                              "value": {
                                "@class": "DV_TEXT",
                                "value": "Janice Cox"
                              }
                            }
                          ]
                        },
                        {
                          "@class": "CLUSTER",
                          "name": {
                            "@class": "DV_TEXT",
                            "value": "Address"
                          },
                          "archetype_details": {
                            "@class": "ARCHETYPED",
                            "archetype_id": {
                              "@class": "ARCHETYPE_ID",
                              "value": "openEHR-EHR-CLUSTER.address_uk.v0"
                            },
                            "rm_version": "1.0.1"
                          },
                          "archetype_node_id": "openEHR-EHR-CLUSTER.address_uk.v0",
                          "items": [
                            {
                              "@class": "ELEMENT",
                              "name": {
                                "@class": "DV_TEXT",
                                "value": "Address description"
                              },
                              "archetype_node_id": "at0002",
                              "value": {
                                "@class": "DV_TEXT",
                                "value": "52 simmons St, Leeds"
                              }
                            }
                          ]
                        },
                        {
                          "@class": "CLUSTER",
                          "name": {
                            "@class": "DV_TEXT",
                            "value": "Contact details"
                          },
                          "archetype_details": {
                            "@class": "ARCHETYPED",
                            "archetype_id": {
                              "@class": "ARCHETYPE_ID",
                              "value": "openEHR-EHR-CLUSTER.telecom_uk.v1"
                            },
                            "rm_version": "1.0.1"
                          },
                          "archetype_node_id": "openEHR-EHR-CLUSTER.telecom_uk.v1",
                          "items": [
                            {
                              "@class": "ELEMENT",
                              "name": {
                                "@class": "DV_TEXT",
                                "value": "Comms description"
                              },
                              "archetype_node_id": "at0002",
                              "value": {
                                "@class": "DV_TEXT",
                                "value": "Mobile: 045567 33452"
                              }
                            }
                          ]
                        }
                      ]
                    },
                    {
                      "@class": "ELEMENT",
                      "name": {
                        "@class": "DV_TEXT",
                        "value": "Relationship category"
                      },
                      "archetype_node_id": "at0035",
                      "value": {
                        "@class": "DV_CODED_TEXT",
                        "value": "Main informal carer",
                        "defining_code": {
                          "@class": "CODE_PHRASE",
                          "terminology_id": {
                            "@class": "TERMINOLOGY_ID",
                            "value": "local"
                          },
                          "code_string": "at0037"
                        }
                      }
                    },
                    {
                      "@class": "ELEMENT",
                      "name": {
                        "@class": "DV_TEXT",
                        "value": "Relationship/ role"
                      },
                      "archetype_node_id": "at0030",
                      "value": {
                        "@class": "DV_TEXT",
                        "value": "Daughter"
                      }
                    },
                    {
                      "@class": "ELEMENT",
                      "name": {
                        "@class": "DV_TEXT",
                        "value": "Is next of kin?"
                      },
                      "archetype_node_id": "at0025",
                      "value": {
                        "@class": "DV_BOOLEAN",
                        "value": true
                      }
                    },
                    {
                      "@class": "ELEMENT",
                      "name": {
                        "@class": "DV_TEXT",
                        "value": "Note"
                      },
                      "archetype_node_id": "at0017",
                      "value": {
                        "@class": "DV_TEXT",
                        "value": "Do not call overnight."
                      }
                    }
                  ]
                }
              }
            ]
          }
        ]
      }
    },
    {
      "data": {
        "@class": "COMPOSITION",
        "name": {
          "@class": "DV_TEXT",
          "value": "Relevant Contacts List"
        },
        "uid": {
          "@class": "OBJECT_VERSION_ID",
          "value": "ea5fa88b-5c3e-449b-90af-d8945db2bde4::hcbox.oprn.ehrscape.com::2"
        },
        "archetype_details": {
          "@class": "ARCHETYPED",
          "archetype_id": {
            "@class": "ARCHETYPE_ID",
            "value": "openEHR-EHR-COMPOSITION.health_summary.v1"
          },
          "template_id": {
            "@class": "TEMPLATE_ID",
            "value": "IDCR - Relevant contacts.v0"
          },
          "rm_version": "1.0.1"
        },
        "archetype_node_id": "openEHR-EHR-COMPOSITION.health_summary.v1",
        "language": {
          "@class": "CODE_PHRASE",
          "terminology_id": {
            "@class": "TERMINOLOGY_ID",
            "value": "ISO_639-1"
          },
          "code_string": "en"
        },
        "territory": {
          "@class": "CODE_PHRASE",
          "terminology_id": {
            "@class": "TERMINOLOGY_ID",
            "value": "ISO_3166-1"
          },
          "code_string": "GB"
        },
        "category": {
          "@class": "DV_CODED_TEXT",
          "value": "event",
          "defining_code": {
            "@class": "CODE_PHRASE",
            "terminology_id": {
              "@class": "TERMINOLOGY_ID",
              "value": "openehr"
            },
            "code_string": "433"
          }
        },
        "composer": {
          "@class": "PARTY_IDENTIFIED",
          "name": "Dr Tony Shannon"
        },
        "context": {
          "@class": "EVENT_CONTEXT",
          "start_time": {
            "@class": "DV_DATE_TIME",
            "value": "2017-12-04T11:53:57Z"
          },
          "setting": {
            "@class": "DV_CODED_TEXT",
            "value": "other care",
            "defining_code": {
              "@class": "CODE_PHRASE",
              "terminology_id": {
                "@class": "TERMINOLOGY_ID",
                "value": "openehr"
              },
              "code_string": "238"
            }
          },
          "health_care_facility": {
            "@class": "PARTY_IDENTIFIED",
            "external_ref": {
              "@class": "PARTY_REF",
              "id": {
                "@class": "GENERIC_ID",
                "value": "999999-345",
                "scheme": "2.16.840.1.113883.2.1.4.3"
              },
              "namespace": "NHS-UK",
              "type": "PARTY"
            },
            "name": "Rippleburgh GP Practice"
          }
        },
        "content": [
          {
            "@class": "SECTION",
            "name": {
              "@class": "DV_TEXT",
              "value": "Relevant contacts"
            },
            "archetype_details": {
              "@class": "ARCHETYPED",
              "archetype_id": {
                "@class": "ARCHETYPE_ID",
                "value": "openEHR-EHR-SECTION.relevant_contacts_rcp.v1"
              },
              "rm_version": "1.0.1"
            },
            "archetype_node_id": "openEHR-EHR-SECTION.relevant_contacts_rcp.v1",
            "items": [
              {
                "@class": "ADMIN_ENTRY",
                "name": {
                  "@class": "DV_TEXT",
                  "value": "Relevant contact"
                },
                "archetype_details": {
                  "@class": "ARCHETYPED",
                  "archetype_id": {
                    "@class": "ARCHETYPE_ID",
                    "value": "openEHR-EHR-ADMIN_ENTRY.relevant_contact_rcp.v1"
                  },
                  "rm_version": "1.0.1"
                },
                "archetype_node_id": "openEHR-EHR-ADMIN_ENTRY.relevant_contact_rcp.v1",
                "language": {
                  "@class": "CODE_PHRASE",
                  "terminology_id": {
                    "@class": "TERMINOLOGY_ID",
                    "value": "ISO_639-1"
                  },
                  "code_string": "en"
                },
                "encoding": {
                  "@class": "CODE_PHRASE",
                  "terminology_id": {
                    "@class": "TERMINOLOGY_ID",
                    "value": "IANA_character-sets"
                  },
                  "code_string": "UTF-8"
                },
                "subject": {
                  "@class": "PARTY_SELF"
                },
                "data": {
                  "@class": "ITEM_TREE",
                  "name": {
                    "@class": "DV_TEXT",
                    "value": "Tree"
                  },
                  "archetype_node_id": "at0001",
                  "items": [
                    {
                      "@class": "CLUSTER",
                      "name": {
                        "@class": "DV_TEXT",
                        "value": "Individual person"
                      },
                      "archetype_details": {
                        "@class": "ARCHETYPED",
                        "archetype_id": {
                          "@class": "ARCHETYPE_ID",
                          "value": "openEHR-EHR-CLUSTER.individual_person_uk.v1"
                        },
                        "rm_version": "1.0.1"
                      },
                      "archetype_node_id": "openEHR-EHR-CLUSTER.individual_person_uk.v1",
                      "items": [
                        {
                          "@class": "CLUSTER",
                          "name": {
                            "@class": "DV_TEXT",
                            "value": "Person name"
                          },
                          "archetype_details": {
                            "@class": "ARCHETYPED",
                            "archetype_id": {
                              "@class": "ARCHETYPE_ID",
                              "value": "openEHR-EHR-CLUSTER.person_name.v1"
                            },
                            "rm_version": "1.0.1"
                          },
                          "archetype_node_id": "openEHR-EHR-CLUSTER.person_name.v1",
                          "items": [
                            {
                              "@class": "ELEMENT",
                              "name": {
                                "@class": "DV_TEXT",
                                "value": "Unstructured name"
                              },
                              "archetype_node_id": "at0001",
                              "value": {
                                "@class": "DV_TEXT",
                                "value": "Annette Long n"
                              }
                            }
                          ]
                        },
                        {
                          "@class": "CLUSTER",
                          "name": {
                            "@class": "DV_TEXT",
                            "value": "Contact details"
                          },
                          "archetype_details": {
                            "@class": "ARCHETYPED",
                            "archetype_id": {
                              "@class": "ARCHETYPE_ID",
                              "value": "openEHR-EHR-CLUSTER.telecom_uk.v1"
                            },
                            "rm_version": "1.0.1"
                          },
                          "archetype_node_id": "openEHR-EHR-CLUSTER.telecom_uk.v1",
                          "items": [
                            {
                              "@class": "ELEMENT",
                              "name": {
                                "@class": "DV_TEXT",
                                "value": "Comms description"
                              },
                              "archetype_node_id": "at0002",
                              "value": {
                                "@class": "DV_TEXT",
                                "value": "Mobile: 01345 676767 n"
                              }
                            }
                          ]
                        }
                      ]
                    },
                    {
                      "@class": "ELEMENT",
                      "name": {
                        "@class": "DV_TEXT",
                        "value": "Relationship/ role"
                      },
                      "archetype_node_id": "at0030",
                      "value": {
                        "@class": "DV_TEXT",
                        "value": "Wife"
                      }
                    },
                    {
                      "@class": "ELEMENT",
                      "name": {
                        "@class": "DV_TEXT",
                        "value": "Note"
                      },
                      "archetype_node_id": "at0017",
                      "value": {
                        "@class": "DV_TEXT",
                        "value": "notes n"
                      }
                    }
                  ]
                }
              }
            ]
          }
        ]
      }
    },
    {
      "data": {
        "@class": "COMPOSITION",
        "name": {
          "@class": "DV_TEXT",
          "value": "Relevant Contacts List"
        },
        "uid": {
          "@class": "OBJECT_VERSION_ID",
          "value": "07d7fbb8-88e7-4f69-b901-38395dd36a6b::hcbox.oprn.ehrscape.com::7"
        },
        "archetype_details": {
          "@class": "ARCHETYPED",
          "archetype_id": {
            "@class": "ARCHETYPE_ID",
            "value": "openEHR-EHR-COMPOSITION.health_summary.v1"
          },
          "template_id": {
            "@class": "TEMPLATE_ID",
            "value": "IDCR - Relevant contacts.v0"
          },
          "rm_version": "1.0.1"
        },
        "archetype_node_id": "openEHR-EHR-COMPOSITION.health_summary.v1",
        "language": {
          "@class": "CODE_PHRASE",
          "terminology_id": {
            "@class": "TERMINOLOGY_ID",
            "value": "ISO_639-1"
          },
          "code_string": "en"
        },
        "territory": {
          "@class": "CODE_PHRASE",
          "terminology_id": {
            "@class": "TERMINOLOGY_ID",
            "value": "ISO_3166-1"
          },
          "code_string": "GB"
        },
        "category": {
          "@class": "DV_CODED_TEXT",
          "value": "event",
          "defining_code": {
            "@class": "CODE_PHRASE",
            "terminology_id": {
              "@class": "TERMINOLOGY_ID",
              "value": "openehr"
            },
            "code_string": "433"
          }
        },
        "composer": {
          "@class": "PARTY_IDENTIFIED",
          "name": "Dr Tony Shannon"
        },
        "context": {
          "@class": "EVENT_CONTEXT",
          "start_time": {
            "@class": "DV_DATE_TIME",
            "value": "2018-01-31T09:41:25Z"
          },
          "setting": {
            "@class": "DV_CODED_TEXT",
            "value": "other care",
            "defining_code": {
              "@class": "CODE_PHRASE",
              "terminology_id": {
                "@class": "TERMINOLOGY_ID",
                "value": "openehr"
              },
              "code_string": "238"
            }
          },
          "health_care_facility": {
            "@class": "PARTY_IDENTIFIED",
            "external_ref": {
              "@class": "PARTY_REF",
              "id": {
                "@class": "GENERIC_ID",
                "value": "999999-345",
                "scheme": "2.16.840.1.113883.2.1.4.3"
              },
              "namespace": "NHS-UK",
              "type": "PARTY"
            },
            "name": "Rippleburgh GP Practice"
          }
        },
        "content": [
          {
            "@class": "SECTION",
            "name": {
              "@class": "DV_TEXT",
              "value": "Relevant contacts"
            },
            "archetype_details": {
              "@class": "ARCHETYPED",
              "archetype_id": {
                "@class": "ARCHETYPE_ID",
                "value": "openEHR-EHR-SECTION.relevant_contacts_rcp.v1"
              },
              "rm_version": "1.0.1"
            },
            "archetype_node_id": "openEHR-EHR-SECTION.relevant_contacts_rcp.v1",
            "items": [
              {
                "@class": "ADMIN_ENTRY",
                "name": {
                  "@class": "DV_TEXT",
                  "value": "Relevant contact"
                },
                "archetype_details": {
                  "@class": "ARCHETYPED",
                  "archetype_id": {
                    "@class": "ARCHETYPE_ID",
                    "value": "openEHR-EHR-ADMIN_ENTRY.relevant_contact_rcp.v1"
                  },
                  "rm_version": "1.0.1"
                },
                "archetype_node_id": "openEHR-EHR-ADMIN_ENTRY.relevant_contact_rcp.v1",
                "language": {
                  "@class": "CODE_PHRASE",
                  "terminology_id": {
                    "@class": "TERMINOLOGY_ID",
                    "value": "ISO_639-1"
                  },
                  "code_string": "en"
                },
                "encoding": {
                  "@class": "CODE_PHRASE",
                  "terminology_id": {
                    "@class": "TERMINOLOGY_ID",
                    "value": "IANA_character-sets"
                  },
                  "code_string": "UTF-8"
                },
                "subject": {
                  "@class": "PARTY_SELF"
                },
                "data": {
                  "@class": "ITEM_TREE",
                  "name": {
                    "@class": "DV_TEXT",
                    "value": "Tree"
                  },
                  "archetype_node_id": "at0001",
                  "items": [
                    {
                      "@class": "CLUSTER",
                      "name": {
                        "@class": "DV_TEXT",
                        "value": "Individual person"
                      },
                      "archetype_details": {
                        "@class": "ARCHETYPED",
                        "archetype_id": {
                          "@class": "ARCHETYPE_ID",
                          "value": "openEHR-EHR-CLUSTER.individual_person_uk.v1"
                        },
                        "rm_version": "1.0.1"
                      },
                      "archetype_node_id": "openEHR-EHR-CLUSTER.individual_person_uk.v1",
                      "items": [
                        {
                          "@class": "CLUSTER",
                          "name": {
                            "@class": "DV_TEXT",
                            "value": "Person name"
                          },
                          "archetype_details": {
                            "@class": "ARCHETYPED",
                            "archetype_id": {
                              "@class": "ARCHETYPE_ID",
                              "value": "openEHR-EHR-CLUSTER.person_name.v1"
                            },
                            "rm_version": "1.0.1"
                          },
                          "archetype_node_id": "openEHR-EHR-CLUSTER.person_name.v1",
                          "items": [
                            {
                              "@class": "ELEMENT",
                              "name": {
                                "@class": "DV_TEXT",
                                "value": "Unstructured name"
                              },
                              "archetype_node_id": "at0001",
                              "value": {
                                "@class": "DV_TEXT",
                                "value": "John Smithy test cause 29.12"
                              }
                            }
                          ]
                        },
                        {
                          "@class": "CLUSTER",
                          "name": {
                            "@class": "DV_TEXT",
                            "value": "Contact details"
                          },
                          "archetype_details": {
                            "@class": "ARCHETYPED",
                            "archetype_id": {
                              "@class": "ARCHETYPE_ID",
                              "value": "openEHR-EHR-CLUSTER.telecom_uk.v1"
                            },
                            "rm_version": "1.0.1"
                          },
                          "archetype_node_id": "openEHR-EHR-CLUSTER.telecom_uk.v1",
                          "items": [
                            {
                              "@class": "ELEMENT",
                              "name": {
                                "@class": "DV_TEXT",
                                "value": "Comms description"
                              },
                              "archetype_node_id": "at0002",
                              "value": {
                                "@class": "DV_TEXT",
                                "value": "012345 33452 test 234"
                              }
                            }
                          ]
                        }
                      ]
                    },
                    {
                      "@class": "ELEMENT",
                      "name": {
                        "@class": "DV_TEXT",
                        "value": "Relationship category"
                      },
                      "archetype_node_id": "at0035",
                      "value": {
                        "@class": "DV_CODED_TEXT",
                        "value": "Informal carer",
                        "defining_code": {
                          "@class": "CODE_PHRASE",
                          "terminology_id": {
                            "@class": "TERMINOLOGY_ID",
                            "value": "local"
                          },
                          "code_string": "at0036"
                        }
                      }
                    },
                    {
                      "@class": "ELEMENT",
                      "name": {
                        "@class": "DV_TEXT",
                        "value": "Relationship/ role"
                      },
                      "archetype_node_id": "at0030",
                      "value": {
                        "@class": "DV_TEXT",
                        "value": "Husband"
                      }
                    },
                    {
                      "@class": "ELEMENT",
                      "name": {
                        "@class": "DV_TEXT",
                        "value": "Note"
                      },
                      "archetype_node_id": "at0017",
                      "value": {
                        "@class": "DV_TEXT",
                        "value": "Works abroad. test 1"
                      }
                    }
                  ]
                }
              }
            ]
          }
        ]
      }
    }
  ]
}
